flask_url_shortener/__init__.py
flask_url_shortener/methods.py
flask_url_shortener/models.py
flask_url_shortener-0.0.2.dist-info/METADATA
flask_url_shortener-0.0.2.dist-info/WHEEL
flask_url_shortener-0.0.2.dist-info/top_level.txt
flask_url_shortener-0.0.2.dist-info/RECORD
