Metadata-Version: 2.1
Name: flask-url-shortener
Version: 0.0.2
Summary: Flask Extension for creating and managing shortened URLs.
Author: Mohamed El-Hasnaouy
Author-email: <elhasnaouymed@proton.me>
Keywords: python,flask,url,shortener,url,development
Classifier: Development Status :: 1 - Planning
Classifier: Intended Audience :: Developers
Classifier: Programming Language :: Python :: 3
Classifier: Operating System :: Unix
Classifier: Operating System :: MacOS :: MacOS X
Classifier: Operating System :: Microsoft :: Windows
Requires-Dist: flask
